sybsc/__init__.py
sybsc/data.txt
sybsc-0.2.dist-info/LICENSE
sybsc-0.2.dist-info/METADATA
sybsc-0.2.dist-info/WHEEL
sybsc-0.2.dist-info/top_level.txt
sybsc-0.2.dist-info/RECORD
